{
  "generated": "2026-01-24T02:27:06.776Z",
  "totalPages": 33,
  "specs": [
    {
      "name": "AI",
      "fileName": "AI",
      "components": 10,
      "layout": "Flex Layout"
    },
    {
      "name": "Allocations",
      "fileName": "Allocations",
      "components": 0,
      "layout": "Flex Layout"
    },
    {
      "name": "TransactionRowSkeleton",
      "fileName": "AllTransactions",
      "components": 0,
      "layout": "Flex Layout"
    },
    {
      "name": "AdvancedFilters",
      "fileName": "AllTransactionsOptimized",
      "components": 0,
      "layout": "Flex Layout"
    },
    {
      "name": "glassCard",
      "fileName": "ApiKeys",
      "components": 0,
      "layout": "Flex Layout"
    },
    {
      "name": "ATOExport",
      "fileName": "ATOExport",
      "components": 0,
      "layout": "Grid Layout"
    },
    {
      "name": "TabPanel",
      "fileName": "BankTransactions",
      "components": 0,
      "layout": "Flex Layout"
    },
    {
      "name": "Bills",
      "fileName": "Bills",
      "components": 0,
      "layout": "Grid Layout"
    },
    {
      "name": "Callback",
      "fileName": "Callback",
      "components": 0,
      "layout": "Flex Layout"
    },
    {
      "name": "Categories",
      "fileName": "Categories",
      "components": 0,
      "layout": "Grid Layout"
    },
    {
      "name": "glassCard",
      "fileName": "ConnectorCallback",
      "components": 0,
      "layout": "Flex Layout"
    },
    {
      "name": "glassCard",
      "fileName": "Connectors",
      "components": 0,
      "layout": "Grid Layout"
    },
    {
      "name": "getConditionsCount",
      "fileName": "CustomRules",
      "components": 0,
      "layout": "Grid Layout"
    },
    {
      "name": "Dashboard",
      "fileName": "Dashboard",
      "components": 0,
      "layout": "Grid Layout"
    },
    {
      "name": "AUTO_PLUS_COLORS",
      "fileName": "Email",
      "components": 0,
      "layout": "Flex Layout"
    },
    {
      "name": "EnhancedAllTransactions",
      "fileName": "EnhancedAllTransactions",
      "components": 0,
      "layout": "Flex Layout"
    },
    {
      "name": "Expenses",
      "fileName": "Expenses",
      "components": 0,
      "layout": "Flex Layout"
    },
    {
      "name": "AdvancedFilters",
      "fileName": "ExpensesOptimized",
      "components": 0,
      "layout": "Grid Layout"
    },
    {
      "name": "ForgotPassword",
      "fileName": "ForgotPassword",
      "components": 0,
      "layout": "Flex Layout"
    },
    {
      "name": "Home",
      "fileName": "Home",
      "components": 0,
      "layout": "Flex Layout"
    },
    {
      "name": "COLORS",
      "fileName": "InsightPlus",
      "components": 0,
      "layout": "Grid Layout"
    },
    {
      "name": "LockedPageDemo",
      "fileName": "LockedPageDemo",
      "components": 0,
      "layout": "Grid Layout"
    },
    {
      "name": "REFERRAL_ALLOWED_HOSTS",
      "fileName": "Login",
      "components": 0,
      "layout": "Flex Layout"
    },
    {
      "name": "Plans",
      "fileName": "Plans",
      "components": 0,
      "layout": "Grid Layout"
    },
    {
      "name": "PRIVACY_FRAMEWORKS",
      "fileName": "PrivacyPolicy",
      "components": 0,
      "layout": "Grid Layout"
    },
    {
      "name": "PrivacySettings",
      "fileName": "PrivacySettings",
      "components": 0,
      "layout": "Grid Layout"
    },
    {
      "name": "countries",
      "fileName": "Register",
      "components": 0,
      "layout": "Flex Layout"
    },
    {
      "name": "ResetPassword",
      "fileName": "ResetPassword",
      "components": 0,
      "layout": "Flex Layout"
    },
    {
      "name": "Subscription",
      "fileName": "Subscription",
      "components": 0,
      "layout": "Grid Layout"
    },
    {
      "name": "COLORS",
      "fileName": "Tax",
      "components": 0,
      "layout": "Grid Layout"
    },
    {
      "name": "LEGAL_FRAMEWORKS",
      "fileName": "TermsOfService",
      "components": 0,
      "layout": "Grid Layout"
    },
    {
      "name": "TabPanel",
      "fileName": "TravelExpenses",
      "components": 0,
      "layout": "Grid Layout"
    },
    {
      "name": "useQuery",
      "fileName": "VerifyEmail",
      "components": 15,
      "layout": "Flex Layout"
    }
  ]
}